igwn_lfn2pfn/__init__.py
igwn_lfn2pfn/frames_lfn2pfn.py
igwn_rucio_lfn2pfn-0.0.4.data/scripts/ligo_legacy_frames
igwn_rucio_lfn2pfn-0.0.4.dist-info/LICENSE
igwn_rucio_lfn2pfn-0.0.4.dist-info/METADATA
igwn_rucio_lfn2pfn-0.0.4.dist-info/WHEEL
igwn_rucio_lfn2pfn-0.0.4.dist-info/top_level.txt
igwn_rucio_lfn2pfn-0.0.4.dist-info/RECORD
