Metadata-Version: 2.1
Name: igwn-rucio-lfn2pfn
Version: 0.0.4
Summary: LFN2PFN algorithms for IGWN
Home-page: https://git.ligo.org/rucio/igwn-rucio-lfn2pfn
Author: James Alexander Clark
Author-email: james.clark@ligo.org
License: UNKNOWN
Platform: UNKNOWN
Classifier: Programming Language :: Python :: 2
Classifier: License :: OSI Approved :: GNU General Public License v3 (GPLv3)
Classifier: Operating System :: OS Independent
Requires-Dist: rucio (==1.21.4)
